pytaskexec/__init__.py
pytaskexec/exceptions.py
pytaskexec/pytaskexec.py
tests/__init__.py
tests/conftest.py
tests/test_taskrunner.py
pytaskexec-0.1.0.dist-info/METADATA
pytaskexec-0.1.0.dist-info/WHEEL
pytaskexec-0.1.0.dist-info/top_level.txt
pytaskexec-0.1.0.dist-info/RECORD
