Metadata-Version: 2.4
Name: pytaskexec
Version: 0.1.0
Summary: A lightweight task execution system for concurrent operations in Python
Home-page: https://github.com/anandan-bs/pytaskexec
Author: anandan-bs
Author-email: 
Project-URL: Source, https://github.com/anandan-bs/pytaskexec
Project-URL: Bug Reports, https://github.com/anandan-bs/pytaskexec/issues
Keywords: task,concurrent,async,threading,executor
Classifier: Programming Language :: Python :: 3
Classifier: License :: OSI Approved :: MIT License
Classifier: Operating System :: OS Independent
Requires-Python: >=3.6
Requires-Dist: concurrent-futures; python_version < "3.2"
Dynamic: author
Dynamic: classifier
Dynamic: description
Dynamic: description-content-type
Dynamic: home-page
Dynamic: keywords
Dynamic: project-url
Dynamic: requires-dist
Dynamic: requires-python
Dynamic: summary
